shop_system_models/__init__.py
shop_system_models/__init__.pyi
shop_system_models/consts/__init__.py
shop_system_models/consts/__init__.pyi
shop_system_models/consts/country_codes.py
shop_system_models/consts/country_codes.pyi
shop_system_models/consts/enums.py
shop_system_models/consts/enums.pyi
shop_system_models/consts/messages/admin.py
shop_system_models/consts/messages/locales/en.json
shop_system_models/consts/messages/locales/ru.json
shop_system_models/consts/messages/mapping.py
shop_system_models/deployment_api/__init__.py
shop_system_models/deployment_api/__init__.pyi
shop_system_models/deployment_api/request/authorization.py
shop_system_models/deployment_api/request/bot.py
shop_system_models/deployment_api/request/nocodb.py
shop_system_models/deployment_api/request/premium.py
shop_system_models/deployment_api/request/processes.py
shop_system_models/deployment_api/request/servers.py
shop_system_models/deployment_api/request/services.py
shop_system_models/deployment_api/shared.py
shop_system_models/deployment_api/shared.pyi
shop_system_models/deployment_api/users.py
shop_system_models/deployment_api/users.pyi
shop_system_models/py.typed
shop_system_models/shared.py
shop_system_models/shared.pyi
shop_system_models/shop_api/__init__.py
shop_system_models/shop_api/__init__.pyi
shop_system_models/shop_api/bot/__init__.py
shop_system_models/shop_api/bot/request.py
shop_system_models/shop_api/bot/response.py
shop_system_models/shop_api/commands/__init__.py
shop_system_models/shop_api/commands/request.py
shop_system_models/shop_api/commands/response.py
shop_system_models/shop_api/links.py
shop_system_models/shop_api/processes/__init__.py
shop_system_models/shop_api/processes/request.py
shop_system_models/shop_api/processes/response.py
shop_system_models/shop_api/shared.py
shop_system_models/shop_api/shop/__init__.py
shop_system_models/shop_api/shop/request/__init__.py
shop_system_models/shop_api/shop/request/baskets.py
shop_system_models-1.4.0.dist-info/METADATA
shop_system_models-1.4.0.dist-info/WHEEL
shop_system_models-1.4.0.dist-info/RECORD
