Metadata-Version: 2.4
Name: shop_system_models
Version: 1.4.0
Summary: Shared model definitions for shop system services
Author: Pavel Mulin
Author-email: pavel@tg-shops.com
Requires-Python: >=3.9
Classifier: Programming Language :: Python :: 3
Classifier: Programming Language :: Python :: 3.9
Classifier: Programming Language :: Python :: 3.10
Classifier: Programming Language :: Python :: 3.11
Classifier: Programming Language :: Python :: 3.12
Classifier: Programming Language :: Python :: 3.13
Classifier: Programming Language :: Python :: 3.14
Requires-Dist: pydantic (>=2.10.3)
